aliyunsdkunimkt/__init__.py
aliyunsdkunimkt/endpoint.py
aliyunsdkunimkt/request/__init__.py
aliyunsdkunimkt/request/v20181212/ChangeMediaStatusRequest.py
aliyunsdkunimkt/request/v20181212/ChangeSlotStatusRequest.py
aliyunsdkunimkt/request/v20181212/ChangeTenantStatusRequest.py
aliyunsdkunimkt/request/v20181212/ChangeTenantUserStatusRequest.py
aliyunsdkunimkt/request/v20181212/ChargeLaunchRequest.py
aliyunsdkunimkt/request/v20181212/CheckDeviceRequest.py
aliyunsdkunimkt/request/v20181212/CheckReceivingDetailRequest.py
aliyunsdkunimkt/request/v20181212/CheckTenantBizRequest.py
aliyunsdkunimkt/request/v20181212/CheckUserFinishAdRequest.py
aliyunsdkunimkt/request/v20181212/CountUserRequest.py
aliyunsdkunimkt/request/v20181212/CreateCalculationRequest.py
aliyunsdkunimkt/request/v20181212/CreateFlowRequest.py
aliyunsdkunimkt/request/v20181212/CreateMediaRequest.py
aliyunsdkunimkt/request/v20181212/CreateProxyBrandUserRequest.py
aliyunsdkunimkt/request/v20181212/CreateRuleRequest.py
aliyunsdkunimkt/request/v20181212/CreateSlotRequest.py
aliyunsdkunimkt/request/v20181212/CreateTenantRequest.py
aliyunsdkunimkt/request/v20181212/CreateTenantUserRequest.py
aliyunsdkunimkt/request/v20181212/CreateUnionTaskRequest.py
aliyunsdkunimkt/request/v20181212/CreateUserRequest.py
aliyunsdkunimkt/request/v20181212/CreatesSlotTemplateRequest.py
aliyunsdkunimkt/request/v20181212/DeleteRuleRequest.py
aliyunsdkunimkt/request/v20181212/DeviceApiAddDeviceRequest.py
aliyunsdkunimkt/request/v20181212/EndUnionTaskRequest.py
aliyunsdkunimkt/request/v20181212/GetMainPartListRequest.py
aliyunsdkunimkt/request/v20181212/GetUnionTaskStatusRequest.py
aliyunsdkunimkt/request/v20181212/InnerCallServiceRequest.py
aliyunsdkunimkt/request/v20181212/KeepAliveRequest.py
aliyunsdkunimkt/request/v20181212/ListFlowRequest.py
aliyunsdkunimkt/request/v20181212/ListMediaNameRequest.py
aliyunsdkunimkt/request/v20181212/ListMediaRequest.py
aliyunsdkunimkt/request/v20181212/ListRuleAreaRequest.py
aliyun_python_sdk_unimkt-2.4.8.dist-info/LICENSE
aliyun_python_sdk_unimkt-2.4.8.dist-info/METADATA
aliyun_python_sdk_unimkt-2.4.8.dist-info/WHEEL
aliyun_python_sdk_unimkt-2.4.8.dist-info/top_level.txt
aliyun_python_sdk_unimkt-2.4.8.dist-info/RECORD
